streamlit_luckysheet/__init__.py
streamlit_luckysheet/example.py
streamlit_luckysheet/frontend/build/asset-manifest.json
streamlit_luckysheet/frontend/build/bootstrap.min.css
streamlit_luckysheet/frontend/build/index.html
streamlit_luckysheet/frontend/build/luckyexcel.umd.js
streamlit_luckysheet/frontend/build/luckysheet.umd.js
streamlit_luckysheet/frontend/build/luckysheet.umd.js.map
streamlit_luckysheet/frontend/build/service-worker.js
streamlit_luckysheet/frontend/build/serviceWorker.js
streamlit_luckysheet/frontend/build/assets/iconfont/Anton-Regular.ttf
streamlit_luckysheet/frontend/build/assets/iconfont/HanaleiFill-Regular.ttf
streamlit_luckysheet/frontend/build/assets/iconfont/Pacifico-Regular.ttf
streamlit_luckysheet/frontend/build/assets/iconfont/demo.css
streamlit_luckysheet/frontend/build/assets/iconfont/demo_index.html
streamlit_luckysheet/frontend/build/assets/iconfont/iconfont.css
streamlit_luckysheet/frontend/build/assets/iconfont/iconfont.eot
streamlit_luckysheet/frontend/build/assets/iconfont/iconfont.js
streamlit_luckysheet/frontend/build/assets/iconfont/iconfont.json
streamlit_luckysheet/frontend/build/assets/iconfont/iconfont.svg
streamlit_luckysheet/frontend/build/assets/iconfont/iconfont.ttf
streamlit_luckysheet/frontend/build/assets/iconfont/iconfont.woff
streamlit_luckysheet/frontend/build/assets/iconfont/iconfont.woff2
streamlit_luckysheet/frontend/build/backup/assets/iconfont/Anton-Regular.ttf
streamlit_luckysheet/frontend/build/backup/assets/iconfont/HanaleiFill-Regular.ttf
streamlit_luckysheet/frontend/build/backup/assets/iconfont/Pacifico-Regular.ttf
streamlit_luckysheet/frontend/build/backup/assets/iconfont/demo.css
streamlit_luckysheet/frontend/build/backup/assets/iconfont/demo_index.html
streamlit_luckysheet/frontend/build/backup/assets/iconfont/iconfont.css
streamlit_luckysheet/frontend/build/backup/assets/iconfont/iconfont.eot
streamlit_luckysheet/frontend/build/backup/assets/iconfont/iconfont.js
streamlit_luckysheet-0.1.9.dist-info/LICENSE
streamlit_luckysheet-0.1.9.dist-info/METADATA
streamlit_luckysheet-0.1.9.dist-info/WHEEL
streamlit_luckysheet-0.1.9.dist-info/top_level.txt
streamlit_luckysheet-0.1.9.dist-info/RECORD
